jobpoller/__init__.py
jobpoller/config.py
jobpoller/job_processor.py
jobpoller/utils/__init__.py
jobpoller/utils/logger.py
superbright_jobpoller-0.1.0.dist-info/METADATA
superbright_jobpoller-0.1.0.dist-info/WHEEL
superbright_jobpoller-0.1.0.dist-info/top_level.txt
superbright_jobpoller-0.1.0.dist-info/RECORD
