Metadata-Version: 2.4
Name: superbright-jobpoller
Version: 0.1.0
Summary: A library for polling and processing jobs from API endpoints
Home-page: https://github.com/superbright/jobpoller
Author: SuperBright
Author-email: info@superbright.ai
Classifier: Programming Language :: Python :: 3
Classifier: License :: OSI Approved :: MIT License
Classifier: Operating System :: OS Independent
Requires-Python: >=3.6
Requires-Dist: requests>=2.25.0
Dynamic: author
Dynamic: author-email
Dynamic: classifier
Dynamic: description
Dynamic: description-content-type
Dynamic: home-page
Dynamic: requires-dist
Dynamic: requires-python
Dynamic: summary
